LICENSE
MANIFEST.in
README.rst
setup.py
django_settings/__init__.py
django_settings/admin.py
django_settings/api.py
django_settings/cache.py
django_settings/conf.py
django_settings/dataapi.py
django_settings/forms.py
django_settings/lazyimport.py
django_settings/models.py
django_settings/moduleregistry.py
django_settings.egg-info/PKG-INFO
django_settings.egg-info/SOURCES.txt
django_settings.egg-info/dependency_links.txt
django_settings.egg-info/not-zip-safe
django_settings.egg-info/top_level.txt
django_settings/management/__init__.py
django_settings/management/commands/__init__.py
django_settings/management/commands/settings_initialize.py
django_settings/templates/admin/django_settings/change_form.html
django_settings/templates/admin/django_settings/change_list.html
django_settings/templatetags/__init__.py
django_settings/templatetags/settings_admin_urls.py