Metadata-Version: 1.1
Name: django-settings
Version: 1.3.12
Summary: Simple django reusable application for storing project settings in database.
Home-page: http://github.com/jqb/django-settings
Author: Kuba Janoszek
Author-email: kuba.janoszek@gmail.com
License: UNKNOWN
Platform: UNKNOWN
Classifier: Development Status :: 4 - Beta
Classifier: Environment :: Web Environment
Classifier: Intended Audience :: Developers
Classifier: License :: OSI Approved :: BSD License
Classifier: Operating System :: OS Independent
Classifier: Programming Language :: Python
Classifier: Programming Language :: Python :: 2.6
Classifier: Programming Language :: Python :: 2.7
Classifier: Framework :: Django
